setup.py
imssh/__init__.py
imssh/history.py
imssh/parser.py
imssh/pprint.py
imssh/remotessh.py
imssh/scripts.py
imssh/sftp.py
imssh/threads.py
imssh.egg-info/PKG-INFO
imssh.egg-info/SOURCES.txt
imssh.egg-info/dependency_links.txt
imssh.egg-info/requires.txt
imssh.egg-info/top_level.txt
scripts/imssh