Metadata-Version: 2.1
Name: imssh
Version: 0.0.6
Summary: A paramiko based, ssh automation tool.
Home-page: https://github.com/imneonizer/imssh
Author: Nitin Rai
Author-email: mneonizer@gmail.com
License: MIT License
Platform: linux
Platform: unix
Requires-Python: >3.5.2
